setup.py
YanShi2/Yanshi.py
YanShi2/__init__.py
Yanshi.egg-info/PKG-INFO
Yanshi.egg-info/SOURCES.txt
Yanshi.egg-info/dependency_links.txt
Yanshi.egg-info/top_level.txt