Metadata-Version: 2.1
Name: Yanshi
Version: 0.0.20230809
Summary: ???
Home-page: https://github.com/
Author: Tim Daniel Walt
Author-email: 1330274738@qq.com
Classifier: Programming Language :: Python :: 3
Classifier: License :: OSI Approved :: MIT License
Classifier: Operating System :: OS Independent
